eoq3pyecorempl/__init__.py
eoq3pyecorempl/pyecoreworkspacempl.py
eoq3pyecorempl/Models/WorkspaceMdbModelGenerate.py
eoq3pyecorempl/Models/XmlResourceModelGenerate.py
eoq3pyecorempl/workspacemdbmodel/__init__.py
eoq3pyecorempl/workspacemdbmodel/workspacemdbmodel.py
eoq3pyecorempl/xmlresourcemodel/__init__.py
eoq3pyecorempl/xmlresourcemodel/xmlresourcemodel.py
eoq3pyecorempl-2.9.4.dist-info/licenses/LICENSE
eoq3pyecorempl-2.9.4.dist-info/METADATA
eoq3pyecorempl-2.9.4.dist-info/WHEEL
eoq3pyecorempl-2.9.4.dist-info/top_level.txt
eoq3pyecorempl-2.9.4.dist-info/RECORD
