Metadata-Version: 2.4
Name: eoq3pyecorempl
Version: 2.9.4
Summary: A model persistance layer for EOQ3 based on pyecore
Author-email: Bjoern Annighoefer <bjoern.annighoefer@ils.uni-stuttgart.de>
Project-URL: Homepage, https://gitlab.com/eoq/py/eoq3pyecorempl
Project-URL: Issues, https://gitlab.com/eoq/py/eoq3pyecorempl/-/issues
Classifier: Programming Language :: Python :: 3
Classifier: License :: OSI Approved :: MIT License
Classifier: Operating System :: OS Independent
Requires-Python: >=3.10
License-File: LICENSE
Requires-Dist: eoq3
Requires-Dist: eoq3pyecoreutils
Dynamic: license-file
